[{
  "name": "Aprenda a programar",
  "url": "http://www.jmonteiro.com/aprendaaprogramar/",
  "type": "tutorial",
  "tags": [
    "iniciante"
  ],
  "author": {
    "name": "Diversos",
    "url": ""
  }
}, {
  "name": "Ruby Aprenda a programar na linguagem mais divertida",
  "url": "http://www.casadocodigo.com.br/products/livro-ruby",
  "type": "livro",
  "tags": [
    "livro",
    "ebook"
  ],
  "paid": true,
  "author": {
    "name": "Lucas Souza",
    "url": "https://github.com/lucasas"
  }
}]